{
  "kind": "collectionType",
  "collectionName": "joins",
  "info": {
    "singularName": "join",
    "pluralName": "joins",
    "displayName": "join"
  },
  "options": {
    "draftAndPublish": true
  },
  "pluginOptions": {},
  "attributes": {
    "firstname": {
      "type": "string",
      "required": true,
      "minLength": 1
    },
    "lastname": {
      "type": "string",
      "required": true,
      "minLength": 1
    },
    "email": {
      "type": "email",
      "required": true
    },
    "contact": {
      "type": "string",
      "required": true
    },
    "linkedin": {
      "type": "string",
      "required": false
    },
    "location": {
      "type": "string",
      "required": true
    },
    "skills": {
      "type": "string",
      "required": true
    },
    "resume": {
      "type": "string"
    }
  }
}
